license.txt
setup.cfg
setup.py
lftk/__init__.py
lftk/derivation_collector.py
lftk/lftk.py
lftk/utils.py
lftk.egg-info/PKG-INFO
lftk.egg-info/SOURCES.txt
lftk.egg-info/dependency_links.txt
lftk.egg-info/requires.txt
lftk.egg-info/top_level.txt
lftk/derivation/__init__.py
lftk/derivation/avgentity.py
lftk/derivation/avgpartofspeech.py
lftk/derivation/avgworddiff.py
lftk/derivation/avgwordsent.py
lftk/derivation/foundation_collector.py
lftk/derivation/lexicalvariation.py
lftk/derivation/readformula.py
lftk/derivation/readtimeformula.py
lftk/derivation/typetokenratio.py
lftk/foundation/__init__.py
lftk/foundation/entity.py
lftk/foundation/partofspeech.py
lftk/foundation/worddiff.py
lftk/foundation/wordsent.py
lftk/resources/AoA_ratings_bry.csv
lftk/resources/AoA_ratings_kup.csv
lftk/resources/feature_map.json
lftk/resources/subtlex_us.csv