Metadata-Version: 1.0
Name: lftk
Version: 1.0.8
Summary: Comprehensive Handcrafted Linguistic Features Extraction in Python
Home-page: https://github.com/brucewlee/lftk
Author: Bruce W. Lee
Author-email: brucelws@seas.upenn.edu
License: CC BY-NC 4.0
Keywords: handcrafted linguistic feature
Platform: UNKNOWN
